{
  "trainingData": {
    "balance_queries": {
      "en": ["What is my balance", "Check my balance", "How much money do I have", "Show my account balance", "My current balance"],
      "hi": ["मेरा बैलेंस क्या है", "मेरा खाता बैलेंस", "मेरे पास कितना पैसा है", "बैलेंस दिखाओ", "मेरा वर्तमान बैलेंस"],
      "mr": ["माझे शिल्लक काय आहे", "माझे खाते शिल्लक", "माझ्याकडे किती पैसे आहेत", "शिल्लक दाखवा", "माझे वर्तमान शिल्लक"]
    },
    "transfer_queries": {
      "en": ["Transfer money", "Send funds", "Make a transfer", "Send money to", "I want to transfer"],
      "hi": ["पैसे भेजो", "पैसे ट्रांसफर करो", "धन हस्तांतरण", "पैसा भेजना है", "ट्रांसफर करना चाहता हूँ"],
      "mr": ["पैसे पाठवा", "पैसे हस्तांतरित करा", "निधि स्थानांतरण", "पैसा पाठवायचा आहे", "हस्तांतरण करू इच्छितः"]
    },
    "transaction_queries": {
      "en": ["Show transactions", "Transaction history", "My recent transactions", "List of transactions"],
      "hi": ["लेनदेन दिखाओ", "लेनदेन का इतिहास", "मेरे हालिया लेनदेन", "लेनदेन की सूची"],
      "mr": ["व्यवहार दाखवा", "लेनदेन इतिहास", "माझे अलीकडील व्यवहार", "व्यवहार यादी"]
    },
    "account_details": {
      "en": ["Account details", "My account info", "Customer information", "Account information"],
      "hi": ["खाता विवरण", "मेरा खाता जानकारी", "ग्राहक जानकारी", "खाते की जानकारी"],
      "mr": ["खाते तपशील", "माझी खाते माहिती", "ग्राहक माहिती", "खाते माहिती"]
    }
  },
  "responses": {
    "balance_response": {
      "en": "Your current balance is ₹{balance}. Account: {accNo}",
      "hi": "आपका वर्तमान बैलेंस ₹{balance} है। खाता: {accNo}",
      "mr": "आपले वर्तमान शिल्लक ₹{balance} आहे। खाते: {accNo}"
    },
    "pin_required": {
      "en": "For security, please provide your 4-digit PIN to proceed.",
      "hi": "सुरक्षा के लिए, कृपया आगे बढ़ने के लिए अपना 4-अंकीय PIN दर्ज करें।",
      "mr": "सुरक्षेसाठी, कृपया पुढे जाण्यासाठी आपला 4-अंकी PIN प्रदान करा।"
    },
    "pin_invalid": {
      "en": "Invalid PIN. Please try again.",
      "hi": "अमान्य PIN। कृपया पुनः प्रयास करें।",
      "mr": "अमान्य PIN। कृपया पुन्हा प्रयत्न करा।"
    },
    "transfer_help": {
      "en": "To transfer funds, please provide the beneficiary name and amount.",
      "hi": "धन हस्तांतरित करने के लिए, कृपया लाभार्थी का नाम और राशि प्रदान करें।",
      "mr": "निधी हस्तांतरित करण्यासाठी, कृपया लाभार्थीचे नाव आणि रक्कम प्रदान करा।"
    },
    "greeting": {
      "en": "Hello! I'm Nova, your AI banking assistant. How can I help you today?",
      "hi": "नमस्ते! मैं नोवा हूँ, आपका AI बैंकिंग सहायक। आज मैं आपकी कैसे मदद कर सकता हूँ?",
      "mr": "नमस्कार! मी नोवा आहे, आपला AI बँकिंग सहायक। आज मी आपलाकी कसा मदत करू शकतो?"
    }
  },
  "intents": {
    "balance": {
      "requires_pin": true,
      "action": "fetch_balance"
    },
    "transfer": {
      "requires_pin": true,
      "action": "process_transfer"
    },
    "transactions": {
      "requires_pin": false,
      "action": "fetch_transactions"
    },
    "account_info": {
      "requires_pin": true,
      "action": "fetch_account_details"
    }
  }
}
